orbis_plugin_storage_cache_webservice_results/__init__.py
orbis_plugin_storage_cache_webservice_results/main.py
orbis_plugin_storage_cache_webservice_results-2.2.4.dist-info/LICENSE
orbis_plugin_storage_cache_webservice_results-2.2.4.dist-info/METADATA
orbis_plugin_storage_cache_webservice_results-2.2.4.dist-info/WHEEL
orbis_plugin_storage_cache_webservice_results-2.2.4.dist-info/top_level.txt
orbis_plugin_storage_cache_webservice_results-2.2.4.dist-info/RECORD
